setup.py
heft/__init__.py
heft/core.py
heft/util.py
heft.egg-info/PKG-INFO
heft.egg-info/SOURCES.txt
heft.egg-info/dependency_links.txt
heft.egg-info/not-zip-safe
heft.egg-info/top_level.txt