Metadata-Version: 1.0
Name: heft
Version: 0.1
Summary: A static scheduling heuristic
Home-page: http://github.com/mroclin/heft
Author: Matthew Rocklin
Author-email: mrocklin@gmail.com
License: BSD
Platform: UNKNOWN
